_pywincffi.pyd
pywincffi/__init__.py
pywincffi/exceptions.py
pywincffi/core/__init__.py
pywincffi/core/checks.py
pywincffi/core/dist.py
pywincffi/core/logger.py
pywincffi/core/typesbase.py
pywincffi/core/cdefs/headers/constants.h
pywincffi/core/cdefs/headers/functions.h
pywincffi/core/cdefs/headers/structs.h
pywincffi/core/cdefs/headers/typedefs.h
pywincffi/core/cdefs/sources/main.c
pywincffi/dev/__init__.py
pywincffi/dev/lint.py
pywincffi/dev/release.py
pywincffi/dev/testutil.py
pywincffi/kernel32/__init__.py
pywincffi/kernel32/comms.py
pywincffi/kernel32/console.py
pywincffi/kernel32/events.py
pywincffi/kernel32/file.py
pywincffi/kernel32/handle.py
pywincffi/kernel32/overlapped.py
pywincffi/kernel32/pipe.py
pywincffi/kernel32/process.py
pywincffi/kernel32/synchronization.py
pywincffi/user32/__init__.py
pywincffi/user32/synchronization.py
pywincffi/wintypes/__init__.py
pywincffi/wintypes/functions.py
pywincffi/wintypes/objects.py
pywincffi/wintypes/structures.py
pywincffi/ws2_32/__init__.py
pywincffi/ws2_32/events.py
pywincffi-0.5.0.dist-info/DESCRIPTION.rst
pywincffi-0.5.0.dist-info/METADATA
pywincffi-0.5.0.dist-info/RECORD
pywincffi-0.5.0.dist-info/WHEEL
pywincffi-0.5.0.dist-info/metadata.json
pywincffi-0.5.0.dist-info/top_level.txt
