Metadata-Version: 2.0
Name: pywincffi
Version: 0.5.0
Summary: A Python library which wraps Windows functions using CFFI
Home-page: http://github.com/opalmer/pywincffi
Author: Oliver Palmer
Author-email: oliverpalmer@opalmer.com
License: UNKNOWN
Platform: UNKNOWN
Classifier: Development Status :: 5 - Beta
Classifier: Intended Audience :: Developers
Classifier: License :: OSI Approved :: MIT License
Classifier: Natural Language :: English
Classifier: Environment :: Win32 (MS Windows)
Classifier: Operating System :: Microsoft :: Windows
Classifier: Programming Language :: Python :: 2.7
Classifier: Programming Language :: Python :: 3
Classifier: Programming Language :: Python :: Implementation :: CPython
Classifier: Programming Language :: Python :: Implementation :: PyPy
Classifier: Topic :: Software Development :: Libraries
Requires-Dist: cffi (>=1.6.0)
Requires-Dist: six
